{"table_name":"Heart Disease Dataset (Comprehensive)","columns":[{"id":"heart-statlog-cleveland-hungary-final##age","label":"age"},{"id":"heart-statlog-cleveland-hungary-final##sex","label":"sex"},{"id":"heart-statlog-cleveland-hungary-final##chest pain type","label":"chest pain type"},{"id":"heart-statlog-cleveland-hungary-final##resting bp s","label":"resting bp s"},{"id":"heart-statlog-cleveland-hungary-final##cholesterol","label":"cholesterol"},{"id":"heart-statlog-cleveland-hungary-final##fasting blood sugar","label":"fasting blood sugar"},{"id":"heart-statlog-cleveland-hungary-final##resting ecg","label":"resting ecg"},{"id":"heart-statlog-cleveland-hungary-final##max heart rate","label":"max heart rate"},{"id":"heart-statlog-cleveland-hungary-final##exercise angina","label":"exercise angina"},{"id":"heart-statlog-cleveland-hungary-final##oldpeak","label":"oldpeak"},{"id":"heart-statlog-cleveland-hungary-final##ST slope","label":"ST slope"},{"id":"heart-statlog-cleveland-hungary-final##target","label":"target"}]}
{"table_name":"Big Mac Index Data","columns":[{"id":"big-mac-index-data##date","label":"date"},{"id":"big-mac-index-data##iso_a3","label":"iso_a3"},{"id":"big-mac-index-data##currency_code","label":"currency_code"},{"id":"big-mac-index-data##name","label":"name"},{"id":"big-mac-index-data##local_price","label":"local_price"},{"id":"big-mac-index-data##dollar_ex","label":"dollar_ex"},{"id":"big-mac-index-data##dollar_price","label":"dollar_price"},{"id":"big-mac-index-data##USD_raw","label":"USD_raw"},{"id":"big-mac-index-data##EUR_raw","label":"EUR_raw"},{"id":"big-mac-index-data##GBP_raw","label":"GBP_raw"},{"id":"big-mac-index-data##JPY_raw","label":"JPY_raw"},{"id":"big-mac-index-data##CNY_raw","label":"CNY_raw"},{"id":"big-mac-index-data##GDP_dollar","label":"GDP_dollar"},{"id":"big-mac-index-data##adj_price","label":"adj_price"},{"id":"big-mac-index-data##USD_adjusted","label":"USD_adjusted"},{"id":"big-mac-index-data##EUR_adjusted","label":"EUR_adjusted"},{"id":"big-mac-index-data##GBP_adjusted","label":"GBP_adjusted"},{"id":"big-mac-index-data##JPY_adjusted","label":"JPY_adjusted"},{"id":"big-mac-index-data##CNY_adjusted","label":"CNY_adjusted"}]}
{"table_name":"Covid-19 Global Dataset","columns":[{"id":"covid19-global-dataset##date","label":"date"},{"id":"covid19-global-dataset##country","label":"country"},{"id":"covid19-global-dataset##cumulative_total_cases","label":"cumulative_total_cases"},{"id":"covid19-global-dataset##daily_new_cases","label":"daily_new_cases"},{"id":"covid19-global-dataset##active_cases","label":"active_cases"},{"id":"covid19-global-dataset##cumulative_total_deaths","label":"cumulative_total_deaths"},{"id":"covid19-global-dataset##daily_new_deaths","label":"daily_new_deaths"},{"id":"covid19-global-dataset##continent","label":"continent"},{"id":"covid19-global-dataset##total_confirmed","label":"total_confirmed"},{"id":"covid19-global-dataset##total_deaths","label":"total_deaths"},{"id":"covid19-global-dataset##total_recovered","label":"total_recovered"},{"id":"covid19-global-dataset##active_cases","label":"active_cases"},{"id":"covid19-global-dataset##serious_or_critical","label":"serious_or_critical"},{"id":"covid19-global-dataset##total_cases_per_1m_population","label":"total_cases_per_1m_population"},{"id":"covid19-global-dataset##total_deaths_per_1m_population","label":"total_deaths_per_1m_population"},{"id":"covid19-global-dataset##total_tests","label":"total_tests"},{"id":"covid19-global-dataset##total_tests_per_1m_population","label":"total_tests_per_1m_population"},{"id":"covid19-global-dataset##population","label":"population"}]}
